bech32ref/__init__.py
bech32ref/segwit_addr.py
bech32ref/tests.py
bech32ref-0.1.0.dist-info/METADATA
bech32ref-0.1.0.dist-info/WHEEL
bech32ref-0.1.0.dist-info/RECORD
