Metadata-Version: 2.1
Name: bech32ref
Version: 0.1.0
Summary: A bech32 implemenation, slightly modified to allow for >90char strings
License: MIT
Author: niftynei
Author-email: niftynei@gmail.com
Requires-Python: >=3.10,<4.0
Classifier: License :: OSI Approved :: MIT License
Classifier: Programming Language :: Python :: 3
Classifier: Programming Language :: Python :: 3.10
Classifier: Programming Language :: Python :: 3.11
